.coveragerc
.travis.yml
LICENSE
MANIFEST.in
README.rst
setup.cfg
setup.py
Mopidy_BeetsLocal.egg-info/PKG-INFO
Mopidy_BeetsLocal.egg-info/SOURCES.txt
Mopidy_BeetsLocal.egg-info/dependency_links.txt
Mopidy_BeetsLocal.egg-info/entry_points.txt
Mopidy_BeetsLocal.egg-info/not-zip-safe
Mopidy_BeetsLocal.egg-info/requires.txt
Mopidy_BeetsLocal.egg-info/top_level.txt
Mopidy_BeetsLocal.egg-info/.AppleDouble/.Parent
mopidy_beetslocal/__init__.py
mopidy_beetslocal/actor.py
mopidy_beetslocal/ext.conf
mopidy_beetslocal/library.py
tests/__init__.py
tests/test_extension.py