Metadata-Version: 1.1
Name: Mopidy-BeetsLocal
Version: 0.0.9
Summary: Access local beets library
Home-page: https://github.com/rawdlite/mopidy-beets-local
Author: Tom Roth
Author-email: rawdlite@googlemail.com
License: Apache License, Version 2.0
Platform: UNKNOWN
Classifier: Environment :: No Input/Output (Daemon)
Classifier: Intended Audience :: End Users/Desktop
Classifier: License :: OSI Approved :: Apache Software License
Classifier: Operating System :: OS Independent
Classifier: Programming Language :: Python :: 2
Classifier: Topic :: Multimedia :: Sound/Audio :: Players
